tkla_sqlite_client/__init__.py
tkla_sqlite_client/builder.py
tkla_sqlite_client/core.py
tkla_sqlite_client/logger.py
tkla_sqlite_client/utils.py
tkla_sqlite_client-0.1.0.dist-info/METADATA
tkla_sqlite_client-0.1.0.dist-info/WHEEL
tkla_sqlite_client-0.1.0.dist-info/top_level.txt
tkla_sqlite_client-0.1.0.dist-info/RECORD
