Metadata-Version: 2.4
Name: tkla_sqlite_client
Version: 0.1.0
Summary: Cliente ligero para SQLite con SQL crudo y sin ORM
Home-page: https://github.com/LOVENXON/tkla_sqlite_client
Author: Lovenson Pierre
Author-email: lovesonpierre25@gmail.com
License: MIT
Classifier: Programming Language :: Python :: 3
Classifier: License :: OSI Approved :: MIT License
Classifier: Operating System :: OS Independent
Requires-Python: >=3.7
